jvol/__init__.py
jvol/decoding.py
jvol/encoding.py
jvol/io.py
jvol/jvol.py
jvol/timer.py
jvol/transforms.py
jvol/types.py
jvol/cli/__init__.py
jvol/cli/convert.py
jvol-0.1.0.dist-info/LICENSE
jvol-0.1.0.dist-info/METADATA
jvol-0.1.0.dist-info/WHEEL
jvol-0.1.0.dist-info/entry_points.txt
jvol-0.1.0.dist-info/top_level.txt
jvol-0.1.0.dist-info/RECORD
